promediapaket/__init__.py
promediapaket/ffmpeg.py
promediapaket/player.py
promediapaket/pmp_info.py
promediapaket/pmp_tool.py
promediapaket/promediapaket.py
promediapaket/utils.py
promediapaket/zip.py
promediapaket-0.1.0.dist-info/licenses/LICENSE
promediapaket-0.1.0.dist-info/METADATA
promediapaket-0.1.0.dist-info/WHEEL
promediapaket-0.1.0.dist-info/top_level.txt
promediapaket-0.1.0.dist-info/RECORD
