Metadata-Version: 2.4
Name: promediapaket
Version: 0.1.0
Summary: Tools for Managing PMP Files
Author-email: Jan Erik Mühlwald <problemo@problemo.pro>
License-Expression: MIT
Project-URL: Homepage, https://github.com/Problemo57/promediapaket
Project-URL: Issues, https://github.com/Problemo57/promediapaket/issues
Classifier: Programming Language :: Python :: 3
Classifier: Operating System :: OS Independent
Requires-Python: >=3.9
License-File: LICENSE
Dynamic: license-file
